{
    "presProps.xml": [
        "rId3"
    ],
    "viewProps.xml": [
        "rId4"
    ],
    "tableStyles.xml": [
        "rId6"
    ],
    "printerSettings/printerSettings1.bin": [
        "rId2"
    ],
    "../customXml/item1.xml": [
        "rId7"
    ],
    "../customXml/item2.xml": [
        "rId8"
    ],
    "../customXml/item3.xml": [
        "rId9"
    ],
    "changesInfos/changesInfo1.xml": [
        "rId10"
    ],
    "commentAuthors.xml": [
        "rId11"
    ],
    "handoutMasters/handoutMaster1.xml": [
        "rId12"
    ],
    "notesMasters/notesMaster1.xml": [
        "rId13"
    ],
    "revisionInfo.xml": [
        "rId14"
    ],
    "slideMasters/slideMaster1.xml": [
        "rId15"
    ],
    "slideMasters/slideMaster2.xml": [
        "rId16"
    ],
    "slideMasters/slideMaster3.xml": [
        "rId17"
    ],
    "slideMasters/slideMaster4.xml": [
        "rId18"
    ],
    "slides/slide1.xml": [
        "rId19"
    ],
    "slides/slide2.xml": [
        "rId20"
    ],
    "slides/slide3.xml": [
        "rId21"
    ],
    "theme/theme1.xml": [
        "rId22"
    ],
    "slideMasters/slideMaster5.xml": [
        "rId23"
    ],
    "slides/slide4.xml": [
        "rId24"
    ],
    "slides/slide5.xml": [
        "rId25"
    ],
    "theme/theme7.xml": [
        "rId26"
    ]
}